pythonInetCheck/__init__.py
pythonInetCheck/config.py
pythonInetCheck/main.py
pythonInetCheck-0.0.2.dist-info/LICENSE
pythonInetCheck-0.0.2.dist-info/METADATA
pythonInetCheck-0.0.2.dist-info/WHEEL
pythonInetCheck-0.0.2.dist-info/top_level.txt
pythonInetCheck-0.0.2.dist-info/RECORD
